<suite name="RMA_SampleSuite" parallel="none" allow-return-values="true">

	<!--To Set The Executed SuiteName -->
	<parameter name="ExecutedSuiteName" value="RMA_Reg_PerClaimIncurredLimitJIRA6416Suite_GC_07" />	
	
	<parameter name="DataSourceRow" value="1" /><!--To Set The Datasource 
		Row Name From The sheet RMA_TC_002 of File RMASeleniumAutomationTestData -->	

	<!--Verify That RMA Application Is Logged In -->
	<test name="RMA_TC_001">
		<classes>
			<class name="rmaseleniumtestscripts.RMA_TC_001" />
		</classes>
	</test>

	<!--Verify That Required DSN Is Selected In RMA Application -->
	<test name="RMA_TC_002">
		<classes>
			<class name="rmaseleniumtestscripts.RMA_TC_002" />
		</classes>
	</test>
	
	<!--Successful New Users For Supervisory Chain Creation Is Validated Validated -->
	<!--To Set The No. Of Users in supervisory chain -->
	<parameter name="NoOfUsers" value="4" />
	<parameter name="GroupLevel" value="Yes" />
	<test name="RMA_Reg_Super_UserCreation_TC_001">
		<classes>
			<class name="rmaseleniumtestscripts.RMA_Reg_Super_UserCreation_TC_001" />
		</classes>
	</test>
		
	<!--Successful Revert Setting From Utilities Page Is Validated  -->
	<test name="RMA_Reg_Super_DeSelectALLSetting_TC_001">
	<parameter name="LOB" value="GC - General Claims" />
	 	<classes>
			<class name="rmaseleniumtestscripts.RMA_Reg_Super_DeSelectALLSetting_TC_001" />
		</classes>
	</test>	
	
	<!--Successful Set Reserve Limit At User And Validate It On Supervisory Chain -->
	<!--To Set The LOB Based on claim -->
	<test name="RMA_Reg_Super_ReserveLimit_TC_001">
	<parameter name="LOB" value="GC - General Claims" />
	<parameter name="LimitFactor" value="10" />
		<classes>
			<class name="rmaseleniumtestscripts.RMA_Reg_Super_ReserveLimit_TC_001" />
		</classes>
	</test>
		
	<!--Successful Set Per Claim Incurred Limits At User And Validate It On Supervisory Chain -->
	<!--To Set The LOB Based on claim -->
	<test name="RMA_Reg_Super_PerClaimIncurredLimit_TC_001">
	<parameter name="LOB" value="GC - General Claims" />
	<parameter name="LimitFactor" value="20" />
		<classes>
			<class name="rmaseleniumtestscripts.RMA_Reg_Super_PerClaimIncurredLimit_TC_001" />
		</classes>
	</test>			
	
	<!-- RMA-6416 Test Case TC_INCL_043 Is Started-->
	<!--Successful Selection Of Required Settings In User Privilege SetUp Page And Payment Parameter Setup Page Is Validated -->
	 <test name="RMA_Reg_SuperGen_UtilityAndSecuritySettingsForIncurred_TC_001_2">
	 <parameter name="ReserveLimit_Exceeded" value="uncheck" />
	 <parameter name="SupervisoryApproval_Reserve" value="check" />
	 <parameter name="GroupOf_Supervisor" value="check" />
	 <parameter name="Immediate_Supervisor" value="check" />
	 <parameter name="Adjuster_Chain" value="uncheck" />
	 <parameter name="IncurredLimit_Exceeded" value="check" />
	 <parameter name="Enable_ReserveLimit" value="uncheck" />
	 <parameter name="Enable_IncurredLimit" value="uncheck" />
	 	<classes>
			<class name="rmaseleniumtestscripts.RMA_Reg_SuperGen_UtilityAndSecuritySettingsForIncurred_TC_001" />
		</classes>
	</test>		
	
	<!--Successful Corporate General Claim Creation On Providing Mandatory Data Is Validated -->
	 <test name="RMA_Smoke_TC_002_GC_005">
		<classes>
			<class name="rmaseleniumtestscripts.RMA_Smoke_TC_002_GC" />
		</classes>
	</test>	
	
	<!--Successful Reserve Creation Is Validated -->
	 <test name="RMA_Reg_SuperGen_ReserveCreation_TC_001_12">
	 <parameter name="ClassNameForHeader" value="Reserve Is Created Successfully And Is Not Put On Hold Due To Per Claim Incurred LImit And Reserve Limit As Both Enable Incurred Limit And Enable Reserve Limit Settings Are Off On User Privileges Screen" />
	 <parameter name="ClassNameForFirstReserveCreation" value="Yes" />
	 <parameter name="ClassNameForReserveType" value="1" />
	 <parameter name="ClassNameForReserveAmount" value="50" />
	 	<classes>
			<class name="rmaseleniumtestscripts.RMA_Reg_SuperGen_ReserveCreation_TC_001" />
		</classes>
	</test>	
	
	<!--Successful Logout And Login With Selected Zone Is Validated -->
	 <test name="RMA_Reg_SuperGen_LogoutLoginWithZone_TC_001_01">
	 <parameter name="ClassNameForUserName" value="rmaseleniumtestscripts.RMA_Reg_Super_UserCreation_TC_001::UserFirstName[3]" />
	 <parameter name="ClassNameForPassword" value="rmaseleniumtestscripts.RMA_Reg_Super_UserCreation_TC_001::SupervisoryUserPassword" />
	 	<classes>
			<class name="rmaseleniumtestscripts.RMA_Reg_SuperGen_LogoutLoginWithZone_TC_001" />
		</classes>
	</test>	
	<!-- RMA-6416 Test Case TC_INCL_043 Is Ended-->
	
	<!-- Common Settings for RMA-6416 Test Case TC_INCL_044 to TC_INCL_048 -->		
	<!--Successful Selection Of Required Settings In User Privilege SetUp Page And Payment Parameter Setup Page Is Validated -->
	 <test name="RMA_Reg_SuperGen_UtilityAndSecuritySettingsForIncurred_TC_001_01">
	 <parameter name="ReserveLimit_Exceeded" value="uncheck" />
	 <parameter name="SupervisoryApproval_Reserve" value="check" />
	 <parameter name="GroupOf_Supervisor" value="check" />
	 <parameter name="Immediate_Supervisor" value="check" />
	 <parameter name="Adjuster_Chain" value="uncheck" />
	 <parameter name="IncurredLimit_Exceeded" value="check" />
	 <parameter name="Enable_ReserveLimit" value="uncheck" />
	 <parameter name="Enable_IncurredLimit" value="check" />
	 	<classes>
			<class name="rmaseleniumtestscripts.RMA_Reg_SuperGen_UtilityAndSecuritySettingsForIncurred_TC_001" />
		</classes>
	</test>	
	
	<!-- RMA-6416 Test Case TC_INCL_044 Is Started-->
	<!--Successful Corporate General Claim Creation On Providing Mandatory Data Is Validated -->
	 <test name="RMA_Smoke_TC_002_GC">
		<classes>
			<class name="rmaseleniumtestscripts.RMA_Smoke_TC_002_GC" />
		</classes>
	</test>	
	
	<!--Successful 1st Reserve Creation Is Validated -->
	 <test name="RMA_Reg_SuperGen_ReserveCreation_TC_001_01">
	 <parameter name="ClassNameForHeader" value="Reserve Is Created Successfully" />
	 <parameter name="ClassNameForFirstReserveCreation" value="Yes" />
	 <parameter name="ClassNameForReserveType" value="1" />
	 <parameter name="ClassNameForReserveAmount" value="10" />
	 	<classes>
			<class name="rmaseleniumtestscripts.RMA_Reg_SuperGen_ReserveCreation_TC_001" />
		</classes>
	</test>	
	
	<!--Successful 2nd Reserve Creation Is Validated -->
	 <test name="RMA_Reg_SuperGen_ReserveCreation_TC_001_02">
	 <parameter name="ClassNameForHeader" value="Reserve Is Created Successfully" />
	 <parameter name="ClassNameForReserveType" value="2" />
	 <parameter name="ClassNameForReserveAmount" value="10" />	 
	 	<classes>
			<class name="rmaseleniumtestscripts.RMA_Reg_SuperGen_ReserveCreation_TC_001" />
		</classes>
	</test>	
	
	<!--Successful Verify 3rd Reserve Goes On Hold As Per Claim Incurred Limit Is Breached Is Validated -->
	 <test name="RMA_Reg_SuperGen_ReserveCreation_TC_001_03">
	 <parameter name="ClassNameForHeader" value="Reserve Goes On Hold As Per Claim Incurred Limit Is Breached" />
	 <parameter name="ClassNameForReserveType" value="3" />
	 <parameter name="ClassNameForReserveAmount" value="10" />
	 <parameter name="ClassNameForHoldStatus" value="Yes" />
	 <parameter name="ClassNameForVerificationMessage" value="rmaseleniumPOM_UX.RMA_Selenium_POM_VerificationMessage::ExceedPerClaimIncurredLimitsOnHold" />
		<classes>
			<class name="rmaseleniumtestscripts.RMA_Reg_SuperGen_ReserveCreation_TC_001" />
		</classes>
	</test>		
		
	<!--Successful Logout And Login With Selected Zone Is Validated -->
	 <test name="RMA_Reg_SuperGen_LogoutLoginWithZone_TC_001_02">
	 <parameter name="ClassNameForUserName" value="rmaseleniumtestscripts.RMA_Reg_Super_UserCreation_TC_001::UserFirstName[2]" />
	 <parameter name="ClassNameForPassword" value="rmaseleniumtestscripts.RMA_Reg_Super_UserCreation_TC_001::SupervisoryUserPassword" />
	 <parameter name="ClassNameForZoneName" value="Claims" />
	 	<classes>
			<class name="rmaseleniumtestscripts.RMA_Reg_SuperGen_LogoutLoginWithZone_TC_001" />
		</classes>
	</test>		
	
	<!--Successful Verify 3rd Hold Reserve Is Available To Approve On Supervisory Approval Grid And Approved By Manager Is Validated -->
	<test name="RMA_Reg_SuperGen_ReserveApproval_TC_001_01">
	<parameter name="ClassNameForHeader" value="Reserve Is Submitted To Manager And Available To Approve On Supervisory Approval Grid And Approved Successfully By Manager" />
	<parameter name="ClassNameForReserveType" value="rmaseleniumtestscripts.RMA_Reg_SuperGen_ReserveCreation_TC_001::CreatedReserveType[3]" />
	<parameter name="ClassNameForReserveAmount" value="10" />
	<parameter name="ClassNameForIncurredAmount" value="10" />
 	<parameter name="ClassNameForHoldReason" value="Exceeded Per Claim Incurred Limit" />
 	<parameter name="ClassNameForSubmittedByUser" value="3" />
 	<parameter name="ClassNameForSubmittedToUser" value="2" />
 	<parameter name="ClassNameForVerificationMessage" value="rmaseleniumPOM_UX.RMA_Selenium_POM_VerificationMessage::ApproveReserveBySupervisoryManager" />
	  	<classes>
			<class name="rmaseleniumtestscripts.RMA_Reg_SuperGen_ReserveApproval_TC_001" />
		</classes>
	</test>			
	
	<!--Successful Logout And Login With Selected Zone Is Validated -->
	 <test name="RMA_Reg_SuperGen_LogoutLoginWithZone_TC_001_03">
	 <parameter name="ClassNameForUserName" value="rmaseleniumtestscripts.RMA_Reg_Super_UserCreation_TC_001::UserFirstName[3]" />
	 <parameter name="ClassNameForPassword" value="rmaseleniumtestscripts.RMA_Reg_Super_UserCreation_TC_001::SupervisoryUserPassword" />
	 	<classes>
			<class name="rmaseleniumtestscripts.RMA_Reg_SuperGen_LogoutLoginWithZone_TC_001" />
		</classes>
	</test>	
	<!-- RMA-6416 Test Case TC_INCL_044 Is Ended-->
	
	<!-- RMA-6416 Test Case TC_INCL_045 Is Started-->
	<!--Successful Corporate General Claim Creation On Providing Mandatory Data Is Validated -->
	 <test name="RMA_Smoke_TC_002_GC_001">
		<classes>
			<class name="rmaseleniumtestscripts.RMA_Smoke_TC_002_GC" />
		</classes>
	</test>		
	
	<!--Successful 1st Reserve Creation Is Validated -->
	 <test name="RMA_Reg_SuperGen_ReserveCreation_TC_001_04">
	 <parameter name="ClassNameForHeader" value="Reserve Is Created Successfully" />
	 <parameter name="ClassNameForFirstReserveCreation" value="Yes" />
	 <parameter name="ClassNameForReserveType" value="1" />
	 <parameter name="ClassNameForReserveAmount" value="5" />
	 	<classes>
			<class name="rmaseleniumtestscripts.RMA_Reg_SuperGen_ReserveCreation_TC_001" />
		</classes>
	</test>		
		
	<!--Successful 2nd Reserve Creation Is Validated -->
	 <test name="RMA_Reg_SuperGen_ReserveCreation_TC_001_05">
	 <parameter name="ClassNameForHeader" value="Reserve Is Created Successfully" />
	 <parameter name="ClassNameForReserveType" value="2" />
	 <parameter name="ClassNameForReserveAmount" value="10" />
	 	<classes>
			<class name="rmaseleniumtestscripts.RMA_Reg_SuperGen_ReserveCreation_TC_001" />
		</classes>
	</test>	
		
	<!--Successful 1st Reserve Edit Is Validated -->
	 <test name="RMA_Reg_SuperGen_EditReserve_TC_001_01">
	 <parameter name="ClassNameForHeader" value="Reserve Is Updated Successfully" />
	 <parameter name="ClassNameForEditReserveType" value="rmaseleniumtestscripts.RMA_Reg_SuperGen_ReserveCreation_TC_001::CreatedReserveType[1]" />
	 <parameter name="ClassNameForEditReserveAmount" value="10" />
	 	<classes>
			<class name="rmaseleniumtestscripts.RMA_Reg_SuperGen_EditReserve_TC_001" />
		</classes>
	</test>	
	
	<!--Successful Verify On 2nd Reserve Edit Reserve Goes On Hold As Per Claim Incurred Limit Is Breached Is Validated -->
	 <test name="RMA_Reg_SuperGen_EditReserve_TC_001_02">
	 <parameter name="ClassNameForHeader" value="Reserve Is Updated And Goes On Hold As Per Claim Incurred Limit is Breached" />
	 <parameter name="ClassNameForEditReserveType" value="rmaseleniumtestscripts.RMA_Reg_SuperGen_ReserveCreation_TC_001::CreatedReserveType[2]" />
	 <parameter name="ClassNameForEditReserveAmount" value="50" />
	 <parameter name="ClassNameForVerificationMessage" value="rmaseleniumPOM_UX.RMA_Selenium_POM_VerificationMessage::ExceedPerClaimIncurredLimitsOnHold" />
	 <parameter name="ClassNameForHoldStatus" value="Yes" />
	 	<classes>
			<class name="rmaseleniumtestscripts.RMA_Reg_SuperGen_EditReserve_TC_001" />
		</classes>
	</test>		
	
	<!--Successful Logout And Login With Selected Zone Is Validated -->
	 <test name="RMA_Reg_SuperGen_LogoutLoginWithZone_TC_001_04">
	 <parameter name="ClassNameForUserName" value="rmaseleniumtestscripts.RMA_Reg_Super_UserCreation_TC_001::UserFirstName[2]" />
	 <parameter name="ClassNameForPassword" value="rmaseleniumtestscripts.RMA_Reg_Super_UserCreation_TC_001::SupervisoryUserPassword" />
	 <parameter name="ClassNameForZoneName" value="Claims" />
	 	<classes>
			<class name="rmaseleniumtestscripts.RMA_Reg_SuperGen_LogoutLoginWithZone_TC_001" />
		</classes>
	</test>		
	
	<!--Successful Verify 2nd Hold Reserve Is Available To Approve On Supervisory Approval Grid And On Approval By Manager Goes To Senior Manager For Approval Is Validated -->
	<test name="RMA_Reg_SuperGen_ReserveApproval_TC_001_02">
	<parameter name="ClassNameForHeader" value="Reserve Is Available To Approve On Supervisory Approval Grid And On Approval By Manager Goes To Senior Manager For Approval" />
	<parameter name="ClassNameForReserveType" value="rmaseleniumtestscripts.RMA_Reg_SuperGen_ReserveCreation_TC_001::CreatedReserveType[2]" />
	<parameter name="ClassNameForReserveAmount" value="50" />
	<parameter name="ClassNameForIncurredAmount" value="50" />
 	<parameter name="ClassNameForHoldReason" value="Exceeded Per Claim Incurred Limit" />
 	<parameter name="ClassNameForSubmittedByUser" value="3" />
 	<parameter name="ClassNameForSubmittedToUser" value="2" />
 	<parameter name="ClassNameForVerificationMessage" value="rmaseleniumPOM_UX.RMA_Selenium_POM_VerificationMessage::PerClaimIncurredLimitExceedForSupervisoryManager" />
	  	<classes>
			<class name="rmaseleniumtestscripts.RMA_Reg_SuperGen_ReserveApproval_TC_001" />
		</classes>
	</test>			
	
	<!--Successful Logout And Login With Selected Zone Is Validated -->
	 <test name="RMA_Reg_SuperGen_LogoutLoginWithZone_TC_001">
	 <parameter name="ClassNameForUserName" value="rmaseleniumtestscripts.RMA_Reg_Super_UserCreation_TC_001::UserFirstName[0]" />
	 <parameter name="ClassNameForPassword" value="rmaseleniumtestscripts.RMA_Reg_Super_UserCreation_TC_001::SupervisoryUserPassword" />
	 <parameter name="ClassNameForZoneName" value="Claims" />
	 	<classes>
			<class name="rmaseleniumtestscripts.RMA_Reg_SuperGen_LogoutLoginWithZone_TC_001" />
		</classes>
	</test>		
	
	<!--Successful Verify 2nd Hold Reserve Is Available To Approve On Supervisory Approval Grid And Approved By Senior Manager Is Validated -->
	<test name="RMA_Reg_SuperGen_ReserveApproval_TC_001_03">
	<parameter name="ClassNameForHeader" value="Reserve Is Submitted To Senior Manager And Available To Approve On Supervisory Approval Grid And Approved Successfully By Senior Manager" />
	<parameter name="ClassNameForReserveType" value="rmaseleniumtestscripts.RMA_Reg_SuperGen_ReserveCreation_TC_001::CreatedReserveType[2]" />
	<parameter name="ClassNameForReserveAmount" value="50" />
	<parameter name="ClassNameForIncurredAmount" value="50" />
 	<parameter name="ClassNameForHoldReason" value="Exceeded Per Claim Incurred Limit" />
 	<parameter name="ClassNameForSubmittedByUser" value="3" />
 	<parameter name="ClassNameForSubmittedToUser" value="0" />
 	<parameter name="ClassNameForVerificationMessage" value="rmaseleniumPOM_UX.RMA_Selenium_POM_VerificationMessage::ApproveReserveBySupervisoryManager" />
	  	<classes>
			<class name="rmaseleniumtestscripts.RMA_Reg_SuperGen_ReserveApproval_TC_001" />
		</classes>
	</test>			
	
	<!--Successful Logout And Login With Selected Zone Is Validated -->
	 <test name="RMA_Reg_SuperGen_LogoutLoginWithZone_TC_001_05">
	 <parameter name="ClassNameForUserName" value="rmaseleniumtestscripts.RMA_Reg_Super_UserCreation_TC_001::UserFirstName[3]" />
	 <parameter name="ClassNameForPassword" value="rmaseleniumtestscripts.RMA_Reg_Super_UserCreation_TC_001::SupervisoryUserPassword" />
	 	<classes>
			<class name="rmaseleniumtestscripts.RMA_Reg_SuperGen_LogoutLoginWithZone_TC_001" />
		</classes>
	</test>	
	<!-- RMA-6416 Test Case TC_INCL_045 Is Ended-->
	
	<!-- RMA-6416 Test Case TC_INCL_048 Is Started-->		
	<!--Successful Corporate General Claim Creation On Providing Mandatory Data Is Validated -->
	 <test name="RMA_Smoke_TC_002_GC_003">
		<classes>
			<class name="rmaseleniumtestscripts.RMA_Smoke_TC_002_GC" />
		</classes>
	</test>		
	
	<!--Successful 1st Reserve Creation Is Validated -->
	 <test name="RMA_Reg_SuperGen_ReserveCreation_TC_001_07">
	 <parameter name="ClassNameForHeader" value="Reserve Is Created Successfully" />
	 <parameter name="ClassNameForFirstReserveCreation" value="Yes" />
	 <parameter name="ClassNameForReserveType" value="1" />
	 <parameter name="ClassNameForReserveAmount" value="10" />
	 	<classes>
			<class name="rmaseleniumtestscripts.RMA_Reg_SuperGen_ReserveCreation_TC_001" />
		</classes>
	</test>		
	
	<!--Successful 2nd Reserve Creation Is Validated -->
	 <test name="RMA_Reg_SuperGen_ReserveCreation_TC_001_08">
	 <parameter name="ClassNameForHeader" value="Reserve Is Created Successfully" />
	 <parameter name="ClassNameForReserveType" value="2" />
	 <parameter name="ClassNameForReserveAmount" value="10" />
	 	<classes>
			<class name="rmaseleniumtestscripts.RMA_Reg_SuperGen_ReserveCreation_TC_001" />
		</classes>
	</test>		
		
	<!--Successful Payment Creation On 2nd Reserve Is Validated -->
	 <test name="RMA_Reg_SuperGen_PaymentCreation_TC_001_02">	
	 <parameter name="ClassNameForHeader" value="Payment Is Created Successfully" /> 
	 <parameter name="ClassNameForPaymentAmount" value="10" />	 
	 <parameter name="ClassNameForReserveType" value="rmaseleniumtestscripts.RMA_Reg_SuperGen_ReserveCreation_TC_001::CreatedReserveType[2]" />
	 <parameter name="ClassNameForTransactionType" value="1" />
	  	<classes>
			<class name="rmaseleniumtestscripts.RMA_Reg_SuperGen_PaymentCreation_TC_001" />
		</classes>
	</test>		
	
	<!--Successful Verify Payment Is Not Offset As Incurred Limit Breached Is Validated -->
	 <test name="RMA_Reg_SuperGen_PaymentOffset_TC_001_01">	 
	 <parameter name="ClassNameForControlNumber" value="rmaseleniumtestscripts.RMA_Reg_SuperGen_PaymentCreation_TC_001::StrControlNumber" />	 
	 <parameter name="ClassNameForOffsetCase" value="Payment Is Not Offset As Incurred Limit Breached" />
	   	<classes>
			<class name="rmaseleniumtestscripts.RMA_Reg_SuperGen_PaymentOffset_TC_001" />
		</classes>
	</test>		
	<!-- RMA-6416 Test Case TC_INCL_048 Is Ended-->
	
	<!-- RMA-6416 Test Case TC_INCL_047 Is Started-->	
	<!--Successful Corporate General Claim Creation On Providing Mandatory Data Is Validated -->
	 <test name="RMA_Smoke_TC_002_GC_004">
		<classes>
			<class name="rmaseleniumtestscripts.RMA_Smoke_TC_002_GC" />
		</classes>
	</test>		
	
	<!--Successful 1st Reserve Creation Is Validated -->
	 <test name="RMA_Reg_SuperGen_ReserveCreation_TC_001_10">
	 <parameter name="ClassNameForHeader" value="Reserve Is Created Successfully" />
	 <parameter name="ClassNameForFirstReserveCreation" value="Yes" />
	 <parameter name="ClassNameForReserveType" value="1" />
	 <parameter name="ClassNameForReserveAmount" value="10" />
	 	<classes>
			<class name="rmaseleniumtestscripts.RMA_Reg_SuperGen_ReserveCreation_TC_001" />
		</classes>
	</test>		
	
	<!--Successful 2nd Reserve Creation Is Validated -->
	 <test name="RMA_Reg_SuperGen_ReserveCreation_TC_001_11">
	 <parameter name="ClassNameForHeader" value="Reserve Is Created Successfully" />
	 <parameter name="ClassNameForReserveType" value="2" />
	 <parameter name="ClassNameForReserveAmount" value="10" />
	 	<classes>
			<class name="rmaseleniumtestscripts.RMA_Reg_SuperGen_ReserveCreation_TC_001" />
		</classes>
	</test>	
			
	<!--Successful Verify On 1st Reserve, Payment Creation With Insufficient Reserve With Add Reserve Option, A Message Is Displayed As Transaction cannot be made as Per Claim Incurred Limit is exceeded And On Continue Payment Is Created Is Validated -->
	 <test name="RMA_Reg_SuperGen_PaymentWithInsufficientReserve_TC_001">
	 <parameter name="ClassNameForHeader" value="Payment Creation With Insufficient Reserve With Add Reserve Option, A Message Is Displayed As Transaction Cannot Be Made As Per Claim Incurred Limit is Exceeded And On Continue Payment Is Created" />	 
	 <parameter name="ClassNameForLOB" value="GC - General Claims"/>
	 <parameter name="ClassNameForPaymentAmount" value="20" />	 
	 <parameter name="ClassNameForBalanceAmount" value="10" />	
	 <parameter name="ClassNameForReserveType" value="rmaseleniumtestscripts.RMA_Reg_SuperGen_ReserveCreation_TC_001::CreatedReserveType[1]" />
	 <parameter name="ClassNameForTransactionType" value="1" />
	 <parameter name="ClassNameForInsufficientCase" value="Payment With Per Claim Incurred Limit" />	  	
	 <parameter name="ClassNameForInsufficientSubCase" value="Add Reserve And Continue" />	
	 	<classes>
			<class name="rmaseleniumtestscripts.RMA_Reg_SuperGen_PaymentWithInsufficientReserve_TC_001" />
		</classes>
	</test>		
	<!-- RMA-6416 Test Case TC_INCL_047 Is Ended-->
	
	<!-- RMA-6416 Test Case TC_INCL_046 Is Started-->	
	<!--Successful Corporate General Claim Creation On Providing Mandatory Data Is Validated -->
	 <test name="RMA_Smoke_TC_002_GC_002">
		<classes>
			<class name="rmaseleniumtestscripts.RMA_Smoke_TC_002_GC" />
		</classes>
	</test>			
	
	<!--Successful Verify First & Final Payment Is Not Created As Per Claim Incurred Limit Is Exceeded Is Validated -->
	<test name="RMA_Reg_SuperGen_PaymentCreation_TC_001_01">
		<parameter name="ClassNameForHeader" value="First And Final Payment Is Not Created As Per Claim Incurred Limit Is Exceeded" />
		<parameter name="ClassNameForFirstAndFinalPayment" value="true" />
		<parameter name="ClassNameForPaymentAmount" value="30" />
		<parameter name="ClassNameForReserveType" value="1" />
		<parameter name="ClassNameForTransactionType" value="1" />
		<parameter name="ClassNameForVerificationMessage" value="rmaseleniumPOM_UX.RMA_Selenium_POM_VerificationMessage::ExceedPerClaimIncurredLimitPaymentMsg" />
		<classes>
			<class
				name="rmaseleniumtestscripts.RMA_Reg_SuperGen_PaymentCreation_TC_001" />
		</classes>
	</test>
	<!-- RMA-6416 Test Case TC_INCL_046 Is Ended-->	
		
	<!--Successful Revert Setting From Utilities Page Is Validated -->
	<test name="RMA_Reg_Super_DeSelectALLSetting_TC_001_01">
	<parameter name="LOB" value="GC - General Claims" />
	 	<classes>
			<class name="rmaseleniumtestscripts.RMA_Reg_Super_DeSelectALLSetting_TC_001" />
		</classes>
	</test>	
	
	<!-- Successful Verify Existing Users For Supervisory Chain Deletion Is Validated -->
	 <test name="RMA_Reg_Super_UserDeletion_TC_001">
			<classes>
			<class name="rmaseleniumtestscripts.RMA_Reg_Super_UserDeletion_TC_001" />
		</classes>
	</test>
	
<!-- Logout From Application At end -->
	<test name="RMA_Reg_Logout">
		<classes>
			<class name="rmaseleniumtestscripts.RMA_Reg_Logout" />
		</classes>
	</test>
	</suite>