[
    {
        "URL": "https://rma194automation.dxc-rmcl.com/riskmasterux/#/login",
        "Username": "dxc",
        "Password": "dxc123",
        "DSN": "RM202REG_Test3",
        "EntityType": "Banks",
        "PeopleType": "Adjusters",
        "AccountType": "Checking Account",
        "AccountStatus": "Active",
        "DriverType": "Commercial",
        "Department": "Dep",
        "ClaimStatus": "Open",
        "GCClaimType": "Discrimination",
        "GCPolicyLOB": "APV",
        "PCClaimType": "Property",
        "PCPolicyLOB": "Property",
        "PropertyId1": "P001",
        "EmployeeNo": "1234567",
        "VAPolicyLOB": "VA",
        "VAClaimType": "Auto Bodily Injury",
        "ReserveType": "E Expense",
        "ReserveType_Ex": "E Expense",
        "ReserveStatus": "O - Open",
        "AmountType": "350",
        "AutoCheckPayeeType": "O - Other Payees (People & Entities)",
        "AutoCheckTransactionType": "Court Reporting Fees",
        "AutoCheckAmount": "20",
        "ReserveAmount": "1000",
        "LastName": "Kemper",
        "TransactionType": "EXF Expert Witness Fees",
        "EnhNotesType": "Claimant",
        "ExNoteType": "CL Claimant",
        "EventType": "Disability Event",
        "EventStatus": "Open",
        "ModuleSecurityGroup": "Training",
        "WCClaimType": "Lost Time",
        "WCPolicyLOB": "Workers' Comp Voluntary",
        "WCDepartment": "Street",
        "WCClaimStatus": "Open",
        "WCJurisdiction": "Alberta",
        "EmployeeNumber": "12345",
        "LCClaimType": "29MG",
        "LCPolicyLOB": "Life Policy",
        "LCMannerOfDeath": "Accident",
        "LCCauseOfDeath": "Alcohol/Drug Overdose",
        "EstateProbated": "Yes",
        "DeceasedMaritalStatus": "Married",
        "SpouseLiving": "Yes",
        "LifePolicyName": "TEST2 Financial",
        "LifeCoverage": " FE07 FE07 Additional Living Expense",
        "LitType": "Complaint",
        "DisabilityType": "Illness",
        "IllnessType": "Dermatitis",
        "GCCarrierClaimType": "Professional Liability",
        "PolicyName_stest": "STest565464",
        "PolicyName1": "test10",
        "PolicyUnit": "0000054",
        "Country": "Australia",
        "State": "Victoria",
        "DPMCountry": "USA",
        "MedicalStaffStatus": "Active",
        "NumberOfPayments": "2",
        "PayInterval": "Month",
        "DistributionType": "Regular Mail",
        "BankState": "Alberta",
        "BankAccountNo": "025657511",
        "Amount": "50",
        "PayeeTypeClaimant": "C-Claimant",
        "PolicyName2": "test09",
        "PolicyUnit2": "0000056",
        "PolicyCoverage2": "Prem Ops - GL",
        "BankAccount2": "AccountName_TELM",
        "BAccount": "Claim Payment",
        "CheckStatusPPrinted": "P Printed",
        "CheckStatusRReleased": "R Released",
        "St1": "General Claim Parameters",
        "St2": "Reserve",
        "ExNoteType1": "AP Action Plan",
        "ExNoteType2": "CF Confidential",
        "ExNoteType3": "DM damages",
        "Insured": "Street",
        "PlanStatus": "In Effect",
        "Premium": "500",
        "PayPeriodStartDate": "04/21/2021",
        "PreferredPaymentSchedule": "PM - Month",
        "MonthlyPaymentType": "CDT - Date Based",
        "PreferredMonthlyDay": "1 - First",
        "PreferredDayOfWeekforPayments": "D1 - Monday",
        "Quantity_Txt_Benefits": "4",
        "NonOcc_ClaimStatus": "Open",
        "NonOcc_ClaimType": "Long Term Disability",
        "NonOcc_Department": "Street",
        "NonOcc_PolicyLOB": "NonOcc",
        "NonOcc_EmployeeNo": "1234",
        "NonOcc_Payment_ReserveType": "I Indemnity",
        "NonOcc_Payment_TransactionType": "LSS Lump Sum Settlement",
        "NonOcc_Jurisdiction": "Alabama",
        "Period": "M - Months",
        "FromDateHiredOn": "DH - Date Hired",
        "WaitingPeriodFromDisability": "C - Calendar",
        "WaitDurationType": "D - Days",
        "MaximumDurationOfDisabilityPeriod": "D - Days",
        "MaximumDurationOfDisabilityPeriodFrom": "B - Benefit Start Date",
        "DaysType": "Actual Month (Calendar)",
        "ClassName": "Class_Test",
        "DateHired": "04/20/2021",
        "MonthlyRate": "1000",
        "ClaimantName": "Jerry Spiegel Associates, et al",
        "PolicyName": "test10",
        "ClaimentName": "Jerry Spiegel Associates, et al",
        "SecondPolicyClaimentName": "vi'kas Jerry'Spi'ege''l",
        "InsuredName": "Khan 2, Soha Khan",
        "GCPolicyCoverage": "COVF Medical Expense",
        "PolicyTrackingUnit": "Property:0000054",
        "PolicyUnit1": "0000054",
        "PolicyCoverage": "114 Medical Benefits",
        "PolicyLossCode": "NEWCODE",
        "PolicyName_testvik": "testVik03",
        "PolicyDownloadPolicyName": "APV5050",
        "SecondPolicyName": "testVik03",
        "PIOtherPolicy": "PI Other ( Jerry Spiegel Associates, et al)",
        "ClaimPolicyCoverage": "Property:0000054",
        "AutoCheckTransactionTypeVC": "Auto Bodily Injury",
        "TransactionTypeVC": "CRF Court Reporting Fees",
        "ReserveTypeVC": "BI Bodily Injury",
        "PreferredPrintDate": "5",
        "LitigationType": "Contractual",
        "LitigationStatus": "Discovery",
        "ModuleName": "Training",
        "InternalPolicyStatus": "In Effect",
        "InternalPolicyLOB": "GeneralClaim",
        "InternalInsurer": "Insurers",
        "InternalPolicyMco": "Managed Care Organizations",
        "InternalCoverageType": "General Liability",
        "InternalPolicyLimit": "200",
        "InternalGCClaimType": "Property Loss",
        "InternalGCClaimType1": "GC Corporate",
        "InternalInsured": "Street",
        "InternalInsured1": "Department",
        "PropertyId": "P001",
        "InternalPolicyName": "APV5050",
        "InternalPolicyLossCode": "TESTING",
        "IntPolicy1": "APV5050",
        "CourtName": "APN Court",
        "County": "Orange",
        "VenueState": "California",
        "MatterName": "Matter Test",
        "DepositAmount": "100",
        "CombinedPayInterval": "Month",
        "StatementBalance": "100",
        "StatementBalance1": "50",
        "CollectionBalance": "10",
        "PaymentBalance": "5",
        "PriorBalance": "$105.00",
        "BalancePerBankStatement": "$100.00",
        "WorkTransactionType": "IV Investigation Expense",
        "RestrictionTransType": "EXF Expert Witness Fees",
        "PaymentAmount": "50",
        "GCCarrierClaimType1": "Carrier",
        "GCCarrierPolicyLOB": "APV",
        "PolicySystem": "RMSTG",
        "PolicyNametest": "test111",
        "DetailedTrackingClaimant": "Jerry Spiegel Associates, et al",
        "BankAccount": "ICICI",
        "PayeeType": "O-Other Payees (People & Entities)",
        "PolicyCoverage1": "114 Auto Bodily Injury",
        "CarrierPolicyLOSS": "NEWCODE",
        "CarrierReserve": "REC REC",
        "CarrierTransType": "PS Policy State Payment",
        "AmountType1": "20",
        "depositNumber": "123456",
        "CheckStatus_I_Insufficient_Funds": "I Insufficient Funds",
        "QueuedPayment": "101",
        "VoidReasonCode": "Cancelled Payment",
        "HoldTransactionStatus": "H Hold",
        "Claim": "GC - General Claims",
        "InSufficientReserve": "15",
        "InSufficientPayment": "40",
        "InsufficientReserveType": "Expense",
        "UnclaimedDays": "3",
        "Escheatdays": "5",
        "EntityTypePolicyMCO": "Managed Care Organizations",
        "loblistGc": "GC - General Claims",
        "PolicyMCO": "Managed Care Organizations",
        "PolicyCoverage_Auto": "101 Auto Bodily Injury",
        "GCCarrierClaimType2": "General Liability",
        "PolicyName3": "test11",
        "PrioritizeAdjusterWCClaimType": "Lost Time",
        "PrioritizeAdjusterEmployeeNumber": "1234567",
        "PrioritizeAdjusterJurisdiction": "Alabama",
        "PrioritizeAdjusterNONOCCClaimType": "Lost Time",
        "Checks": "Select Checks",
        "FundsDormancyCountry": "United States",
        "FundsDormancyState": "Alabama",
        "FundsDormancyStatus_Unclaimed": "Unclaimed",
        "FundsDormancyStatus_Escheat": "Escheat",
        "EntityTypePolicyMCO_Adjuster": "Adjusters",
        "NR_ReserveType": "E Expense",
        "RecoveryTransactionType": "RR ReserveRecovery",
        "TransactionType_NR": "CRF Court Reporting Fees",
        "RecoveryReserveType": "Rr Recovery1",
        "TransactionType_Loss": "LOS Loss Payment",
        "TransactionType_Expense": "EXP Expense Payment",
        "EXP_ReserveType": "EXP Expense Payment",
        "Loss_ReserveType": "LOS Loss Payment",
        "IdType": "SSN",
        "AddressType": "1099 Address",
        "AddressType1": "Business",
        "EntityLastName": "Banks",
        "AutoAssignAdjusterPrioritize1": "AdjusterWC&NONOCC1",
        "AutoAssignAdjusterPrioritize2": "AdjusterWC&NONOCC2",
        "AutoAssignAdjusterPrioritize3": "AdjusterWC&NONOCC3",
        "AddressMaintenance1": "Test Address1",
        "AddressMaintenance2": "Test Address1",
        "AddressMaintenance3": "Test Address1",
        "CityMaintenance": "Test City",
        "GCCarrierClaimType_ProfessionalLiability": "Professional Liability",
        "PolicyName_test10": "test10",
        "loblistWc": "WC - Worker's Compensation",
        "loblistVc": "VA - Vehicle Accident Claims",
        "loblistPc": "PC - Property Claims",
        "DeductibleRType": "BI Bodily Injury",
        "DeductibleReserveType": "Deductible Expense",
        "DeductibleTransactionType": "Transaction Deductible Expense",
        "DeductibleType_FP": "First Party",
        "DeductibleType_ND": "Not Determined",
        "DeductibleType_NONE": "None",
        "DeductibleType_SIR": "Self Insured Retention",
        "DeductibleType_TP": "Third Party",
        "DeductibleReserveAmount": "100",
        "DeductibleAmount": "50",
        "DeductiblePaymentAmount": "25",
        "DeductibleReserveType_Ex": "E Expense",
        "DeductibleReserveType_Ex1": "DE Deductible Expense",
        "ClientProgramstatus": "RunOff",
        "ClientProgramType": "Domestic",
        "ClientProgramRevenueType": "Flat Fee",
        "StopPay_Requested": "Requested",
        "StopPay_Accepted": "Accepted",
        "StopPay_Rejected": "Rejected",
        "StopPay_UndoReleased": "Undo/Released",
        "StopPay_StopCheckReasonCode": "Missing Check",
        "PolicyCoverage3": "114 Medical Benefits",
        "AutoAssignAdjusterVAClaimType": "Auto Property Damage",
        "AutoAssignAdjusterVAClaimTypeMismatch": "Auto Bodily Injury",
        "AutoAssignAdjusterGCClaimType": "Director & Officers",
        "AutoAssignAdjusterDepartment": "Dep",
        "AutoAssignAdjusterJurisdiction": "California",
        "AutoAssignAdjuster": "Adjuster1",
        "AutoAssignAdjusterPC": "Adjuster2",
        "AutoAssignAdjusterVC": "Adjuster3",
        "AutoAssignAdjusterJurisdictionMismatch": "Arkansas",
        "AutoAssignAdjusterGCClaimTypeMismatch": "Discrimination",
        "AutoAssignAdjusterPCClaimTypeMismatch": "PropertyClaim",
        "AutoAssignAdjusterPCClaimType": "Property Damage",
        "AutoAssignAdjusterWCClaimType": "LostTime",
        "AutoAssignAdjusterWCClaimTypeMismatch": "Medical Only",
        "AutoAssignAdjusterWCJurisdiction": "California",
        "AutoAssignAdjusterEmployeeNumber": "122",
        "AutoAssignAdjusterWC": "Adjuster3",
        "AutoAssignAdjusterNONOCCClaimType": "Long Term Disability",
        "AutoAssignAdjusterNONOCCClaimTypeMismatch": "Short Term Disability",
        "AutoAssignAdjusterNONOCCJurisdiction": "California",
        "AutoAssignAdjusterNONOCCEmployeeNumber": "222",
        "AutoAssignAdjusteNONOCC": "Adjuster5",
        "BackupWithholdingPercentage": "20",
        "MultiAddress_Bank": "hdfc",
        "EmpolyeeNumber": "1234",
        "CheckStatusHold": "H Hold",
        "CheckStatusRDReviewedButDenied": "RD Reviewed But Denied",
        "Period1": "D - Days",
        "Quantity_Txt_Benefits1": "1",
        "Country1": "United States",
        "ModuleName_Administrator": "Administrator",
        "ReserveType_FnF": "M Medical",
        "TransType_FnF": "DB Doctor Bill",
        "PolicyNumberRandom": "Policy Numbers1234",
        "PolicyNumber_TxtBox": "Policy Number",
        "MyPendingClaimAdjusterLastName1": "AutoMyPendingClaim1",
        "MyPendingClaimAdjusterLastName2": "AutoMyPendingClaim2",
        "ClaimStatusClose": "Closed",
        "MyPendingClaimAdjusterLastName3": "AutoMyPendingClaim3",
        "MyPendingClaimAdjusterLastName4": "AutoMyPendingClaim4",
        "Amount1": "60",
        "PolicyLossCode1": "22",
        "CaseManagmentPassword": "9983A-334BC-A589F-53B90-99D1E",
        "EntityStatus_PendingApproval": "Pending Approval",
        "EntityStatus_Approved": "Approved",
        "EntityStatus_Rejected": "Rejected",
        "ModuleName_Training": "Training",
        "PolicyClaimCodeAPV": "APV - APV",
        "PolicyClaimCode101": "101 - 101",
        "PolicyClaimCodeNEWCODE": "NEWCODE - NEWCODE",
        "ReserveType_BI": "BI Bodily Injury",
        "TransactionType_BI": "ABI Auto Bodily Injury",
        "TransactionType_PD": "APD Auto Physical Damage",
        "Code_Contacts": "Contacts",
        "Code_Steps": "Steps",
        "UsePolicyManagmentSystem_ActivationCode": "A40AC-43CAA-347E2-FB52B-9D00D",
        "ClaimType_ErrorsAndOmissions": "Errors & Omissions",
        "ClaimScheduler_TaskTypePPY": "PositivePay",
        "ClaimScheduler_TaskTypeMBR": "MBR",
        "ClaimScheduler_TaskTypePUS": "PUS",
        "ClaimScheduler_TaskTypeMMSEA": "MMSEA",
        "ClaimScheduler_TaskTypeHRInterface": "HR_Interface",
        "ClaimScheduler_TaskTypeCustomImport": "Custom Import",
        "ClaimScheduler_SubTaskNameImport": "Import",
        "ClaimScheduler_SubTaskNameExtract": "Export",
        "ImportFileNamePPY": "Pipe10",
        "ImportFileNameMBR": "PipeN2",
        "MBRImportFileFormat": "Pipe format with multiple",
        "JobStatusCheckIterations": "10",
        "UnZipFileFolderName": "UnZipJobFilesFolder",
        "ZipFileFolderName": "ZipJobFilesFolder",
        "ImportFileExtensionMBR": ".txt",
        "ImportExportProcessLogFileName": "processlog",
        "ProcessLogFileExtension": ".csv",
        "PrefixUniqueTaskName_MBRImport": "MBRImport_",
        "PrefixUniqueTaskName_MBRExport": "MBRExport_",	
	    "PrefixUniqueTaskName_HRInterfaceExport": "HRInterfaceExport_",
        "ImportSpecFileName": "_IMPORT_SpecFile.xlsx",
        "ImportSpecFilePath": "../Functional_TestScripts/ImportSpecFile/",
        "LogFileExtension": ".csv",
        "FaceAmount": "50",
        "Beneficiary1_Reserve_Amount": "60",
        "Beneficiary2_Reserve_Amount": "40",
        "ProofOfDeathDate": "12/20/2023",
        "ProofOfLossDate": "01/25/2024",
        "ProductType":"UL Interest on Proceeds UL",
        "Beneficiary1":"FL Florida",
        "FaceAmountWithCode": "2000",
        "DividendsWithCode": "2000",
        "PaidUpAddsWithCode": "2000",
        "AccidentDeathBenefitWithCode": "2000"
    }
]